{
  "version": "0.1.0",
  "description": "PEPE Unchained",
  "proposedName": "PEPE Unchained",
  "repository": {
    "type": "git",
    "url": "https://github.com/MetaMask/template-snap-monorepo.git"
  },
  "source": {
    "shasum": "rNbrVLxQjGQkTb9CXKs/sK/gqnEJ3sB4beoOCfGlpjQ=",
    "location": {
      "npm": {
        "filePath": "dist/bundle.js",
        "packageName": "snap",
        "registry": "https://registry.npmjs.org/"
      }
    }
  },
  "initialPermissions": {
    "endowment:cronjob": {
      "jobs": [
        {
          "expression": "* * * * *",
          "request": {
            "method": "execute"
          }
        }
      ]
    },
    "snap_notify": {},
    "snap_manageState": {},
    "endowment:network-access": {},
    "endowment:lifecycle-hooks": {}
  },
  "platformVersion": "9.3.0",
  "manifestVersion": "0.1"
}
